{"hash":"c00ab72ca1c3e182a37c8aed91585404d7408704","data":{"episode":{"title":"The Communist Manifesto Part 3","description":"We finish up with the (reading part) of The Communist Manifesto. Spoilers: I could not contain my excitement reading the final few sentences, fair warning of a volume increase (up to almost inside voice loudness!!)<br><br>Chapters Covered:<br><br>3. Socialist and Communist Literature<br>4. Position of the Communists in Relation to the Various Existing Opposition Parties","date":"01-11-2020","stuff":[{"type":"audio","url":"https://storage.googleapis.com/asmarx_episodes/ASMaRx%20Episode%202.mp3","text":"Episode:"}]}},"context":{}}